{   
    "wind":{
    "speed":"Швидкість",
    "degrees":"Напрямок",
    "gust":"Порив",
    "pressure":"Тиск",
    "humidity":"Вологість",
    "rain":"Дощ",
    "snow":"Сніг"
    },
    "day":"Сьогодні",
    "months":{
            "0": "Січня",
            "1": "Лютого",
            "2": "Березня",
            "3": "Квітня",
            "4": "Травня",
            "5": "Червня",
            "6": "Липня",
            "7": "Серпня",
            "8": "Вересня",
            "9": "Жовтня",
            "10": "Листопада",
            "11": "Грудня"
          
    }
    
}